fracDimPy/__init__.py
fracDimPy/generator/__init__.py
fracDimPy/generator/curves.py
fracDimPy/generator/patterns.py
fracDimPy/generator/surfaces.py
fracDimPy/monofractal/__init__.py
fracDimPy/monofractal/box_counting.py
fracDimPy/monofractal/correlation_dimension.py
fracDimPy/monofractal/dfa.py
fracDimPy/monofractal/hurst.py
fracDimPy/monofractal/information_dimension.py
fracDimPy/monofractal/sandbox.py
fracDimPy/monofractal/structural_function.py
fracDimPy/monofractal/variogram.py
fracDimPy/multifractal/__init__.py
fracDimPy/multifractal/custom_epsilon.py
fracDimPy/multifractal/mf_curve.py
fracDimPy/multifractal/mf_dfa.py
fracDimPy/multifractal/mf_image.py
fracDimPy/utils/__init__.py
fracDimPy/utils/data_io.py
fracDimPy/utils/plotting.py
fracdimpy-0.1.3.dist-info/licenses/LICENSE
fracdimpy-0.1.3.dist-info/METADATA
fracdimpy-0.1.3.dist-info/WHEEL
fracdimpy-0.1.3.dist-info/top_level.txt
fracdimpy-0.1.3.dist-info/RECORD
