Metadata-Version: 2.4
Name: FracDimPy
Version: 0.1.3
Summary: A comprehensive Python package for fractal dimension calculation and multifractal analysis
Home-page: https://github.com/Kecoya/FracDimPy
Author: Zhile Han
Author-email: Zhile Han <2667032759@qq.com>
License: GPL-3.0-or-later
Project-URL: Homepage, https://github.com/Kecoya/FracDimPy
Project-URL: Documentation, https://github.com/Kecoya/FracDimPy/blob/main/README.md
Project-URL: Repository, https://github.com/Kecoya/FracDimPy
Project-URL: Issues, https://github.com/Kecoya/FracDimPy/issues
Keywords: fractal,fractal dimension,multifractal,box-counting,Hurst,R/S analysis
Classifier: Development Status :: 3 - Alpha
Classifier: Intended Audience :: Science/Research
Classifier: Topic :: Scientific/Engineering :: Mathematics
Classifier: Topic :: Scientific/Engineering :: Physics
Classifier: License :: OSI Approved :: GNU General Public License v3 (GPLv3)
Classifier: Programming Language :: Python :: 3
Classifier: Programming Language :: Python :: 3.8
Classifier: Programming Language :: Python :: 3.9
Classifier: Programming Language :: Python :: 3.10
Classifier: Programming Language :: Python :: 3.11
Classifier: Programming Language :: Python :: 3.12
Requires-Python: >=3.8
License-File: LICENSE
Requires-Dist: numpy>=1.20.0
Requires-Dist: scipy>=1.7.0
Requires-Dist: matplotlib>=3.3.0
Requires-Dist: pandas>=1.3.0
Requires-Dist: opencv-python>=4.5.0
Requires-Dist: Pillow>=9.0.0
Provides-Extra: dev
Requires-Dist: pytest>=7.0; extra == "dev"
Requires-Dist: pytest-cov>=4.0; extra == "dev"
Requires-Dist: black>=22.0; extra == "dev"
Requires-Dist: flake8>=5.0; extra == "dev"
Requires-Dist: mypy>=0.990; extra == "dev"
Dynamic: author
Dynamic: home-page
Dynamic: license-file
Dynamic: requires-python
